<?xml version='1.0' encoding='utf-8'?>
<odoo>

    <record id="leulit_20240212_1600_form_inherit2" model="ir.ui.view">
        <field name="model">leulit.maintenance_boroscopia</field>
        <field name="inherit_id" ref="leulit_taller.leulit_20240212_1600_form"/>
        <field name="arch" type="xml">
            <xpath expr="//field[@name='resultado_inspeccion']" position="after">
                <notebook colspan="4" >
                    <page string="Documentos firmados">
                        <field name="esignature_docs" colspan="4" nolabel="1" context="{'form_view_ref' : 'leulit_20210112_1138_form'}">
                            <tree>
                                <field name="id"/>
                                <field name="firmado_por" string="Por"/>
                                <field name="name" />
                                <field name="hashcode" /> 
                                <field name="attachment_id"/>
                            </tree>
                        </field>
                    </page>
                </notebook>
            </xpath>
        </field>
    </record>


</odoo>